<?xml version="1.0" encoding="UTF-8" standalone="yes" ?>
<!DOCTYPE genericSFNTTable [
<!ELEMENT genericSFNTTable (dataLine+)>
<!ELEMENT dataLine EMPTY>
<!ATTLIST genericSFNTTable tag CDATA #REQUIRED
	size CDATA #IMPLIED
>
<!ATTLIST dataLine lineNumber CDATA #REQUIRED
	offset CDATA #REQUIRED
	hex CDATA #REQUIRED
	ascii CDATA #IMPLIED
	unicode CDATA #IMPLIED
>
]>

<!--
 
	Ligature caret entries for Narzędzia Sukcesu the logotype font
	Copyright 2012 Grzegorz Rolek

	There's no apparent support for the 'lcar' table in OS X Font Tools,
	not a word on it in documentation of neither Font Tools nor CoreText,
	not even any traces of it in FontToolbox.framework header files,
	but edited and fused by hand this shit works as expected.

-->

<genericSFNTTable tag="lcar">
	
	<dataLine offset="00000000" hex="00010000" /> <!-- Table Version (1.0) -->
	<dataLine offset="00000004" hex="0000" /> <!-- Table Format (divisions as FUnit distances)-->
	
	<dataLine offset="00000006" hex="0006" /> <!-- Lookup Format (single lookup table) -->
	<dataLine offset="00000008" hex="0004" /> <!-- Unit Size -->
	<dataLine offset="0000000A" hex="0001" /> <!-- Number of Units -->
	<dataLine offset="0000000C" hex="0000" /> <!-- Search Range -->
	<dataLine offset="0000000E" hex="0000" /> <!-- Entry Selector -->
	<dataLine offset="00000010" hex="0000" /> <!-- Range Shift -->
	
	<dataLine offset="00000012" hex="0003" /> <!-- Ligature glyph index (the A glyph) -->
	<dataLine offset="00000014" hex="001A" /> <!-- Offset to distance entry -->
	
	<dataLine offset="00000016" hex="FFFF" /> <!-- Special guardian value -->
	<dataLine offset="00000018" hex="0000" /> <!-- Special guardian value -->
	
	<dataLine offset="0000001A" hex="0001" /> <!-- Number of divisions -->
	<dataLine offset="0000001C" hex="0190" /> <!-- Division distance (advance of the A glyph; 400 FUnits) -->

</genericSFNTTable>
